find_the_site/__init__.py
find_the_site/fw.py
find_the_site-0.2.dist-info/LICENSE
find_the_site-0.2.dist-info/WHEEL
find_the_site-0.2.dist-info/METADATA
find_the_site-0.2.dist-info/RECORD
