Metadata-Version: 2.1
Name: find-the-site
Version: 0.2
Summary: Find the site in duckduckgo
Home-page: https://github.com/serhii73/find_the_site
License: MIT
Keywords: find,search,company website,brand website
Author: serhii
Author-email: aserhii@protonmail.com
Requires-Python: >=3.6,<4.0
Classifier: Development Status :: 5 - Production/Stable
Classifier: Environment :: Console
Classifier: License :: OSI Approved :: MIT License
Classifier: Operating System :: POSIX
Classifier: Programming Language :: Python
Classifier: Programming Language :: Python :: 3
Classifier: Programming Language :: Python :: 3.6
Classifier: Programming Language :: Python :: 3.7
Classifier: Programming Language :: Python :: 3.8
Requires-Dist: beautifulsoup4 (>=4.7.1,<5.0.0)
Requires-Dist: requests (>=2.22,<3.0)
Requires-Dist: user-agent (>=0.1.9,<0.2.0)
Project-URL: Repository, https://github.com/serhii73/find_the_site
